flexmap/__init__.py
flexmap-0.1.0.dist-info/WHEEL
flexmap-0.1.0.dist-info/METADATA
flexmap-0.1.0.dist-info/RECORD
